scanvi_explainer/__init__.py
scanvi_explainer/plots.py
scanvi_explainer/scanvi_bootstrapper.py
scanvi_explainer/scanvi_deep.py
scanvi_explainer/utils.py
scanvi_explainer-0.3.1.dist-info/METADATA
scanvi_explainer-0.3.1.dist-info/WHEEL
scanvi_explainer-0.3.1.dist-info/licenses/LICENSE
scanvi_explainer-0.3.1.dist-info/RECORD
