Metadata-Version: 2.3
Name: scanvi-explainer
Version: 0.3.1
Summary: Exapliner of scANVI using SHAP
Project-URL: Homepage, https://github.com/brickmanlab/scanvi-explainer
Project-URL: Documentation, https://scanvi-explainer.readthedocs.io
Project-URL: Repository, https://github.com/brickmanlab/scanvi-explainer.git
Project-URL: Issues, https://github.com/brickmanlab/scanvi-explainer/issues
Project-URL: Changelog, https://github.com/brickmanlab/scanvi-explainer/blob/master/CHANGELOG.md
Author-email: Martin Proks <martin.proks@sund.ku.dk>, Nazmus M Salehin <naz.salehin@sund.ku.dk>
License: MIT License
License-File: LICENSE
Keywords: explainer,interpretability,scanvi,shap
Classifier: Development Status :: 4 - Beta
Classifier: Intended Audience :: Science/Research
Classifier: License :: OSI Approved :: MIT License
Classifier: Programming Language :: Python :: 3.10
Classifier: Topic :: Scientific/Engineering :: Artificial Intelligence
Classifier: Topic :: Scientific/Engineering :: Bio-Informatics
Requires-Python: >=3.10
Requires-Dist: anndata
Requires-Dist: pandas<=2.0
Requires-Dist: pyarrow
Requires-Dist: rich
Requires-Dist: scvi-tools
Requires-Dist: seaborn
Requires-Dist: shap>=0.41.0
Provides-Extra: dev
Requires-Dist: huggingface-hub; extra == 'dev'
Requires-Dist: ipykernel; extra == 'dev'
Requires-Dist: ipywidgets; extra == 'dev'
Requires-Dist: ruff; extra == 'dev'
Provides-Extra: doc
Requires-Dist: myst-nb>=1.1; extra == 'doc'
Requires-Dist: setuptools; extra == 'doc'
Requires-Dist: sphinx-book-theme>=1; extra == 'doc'
Requires-Dist: sphinx>=4.0; extra == 'doc'
Requires-Dist: sphinxcontrib-bibtex>=1; extra == 'doc'
